<!--
Disabled by https-everywhere-checker because:
Fetch error: http://fuzeqna.com/ => https://www.fuzeqna.com/: (6, 'Could not resolve host: fuzeqna.com')
	Nonfunctional domains:

		- welcome.authorize.net		(no https)


	Problematic domains:

		- authorize.net		(works, cert only matches www)

-->
<ruleset name="Authorize.Net" default_off='failed ruleset test'>

	<target host="authorize.net" />
	<target host="*.authorize.net" />
	<target host="authorizenet.com" />
	<target host="www.authorizenet.com" />
	<!--	The fuzeqna.com domain is included to avoid possible
		issues with mixed content. Also, from what one remembers,
		using the Authorize.Net site may involve accessing the
		fuzeqna.com/www.fuzeqna.com domains.
							-->
	<target host="fuzeqna.com" />
	<target host="www.fuzeqna.com" />


	<!--	Not secured by server:
					-->
	<!--securecookie host="^www\.authorize\.net$" name="^PHPSESSID$" /-->

	<securecookie host="^(?:.*\.)?authorize\.net$" name=".+" />


	<rule from="^http://authorize\.net/"
		to="https://www.authorize.net/" />

	<rule from="^http://(account|captcha|content|(?:community\.)?developer|ems|simplecheckout|support|verify|www)\.authorize\.net/"
		to="https://$1.authorize.net/" />

	<rule from="^http://(?:www\.)?authorizenet\.com/"
		to="https://www.authorize.net/" />
	
	<rule from="^http://(?:www\.)?fuzeqna\.com/"
		to="https://www.fuzeqna.com/" />

</ruleset>
