<ruleset name="Český hosting">
    <target host="cesky-hosting.cz" />
    <target host="www.cesky-hosting.cz" />
    <target host="webmail.cesky-hosting.cz" />
    <target host="webmail2.cesky-hosting.cz" />
    <target host="webftp.cesky-hosting.cz" />
    <target host="mysql.cesky-hosting.cz" />
    <target host="pgsql.cesky-hosting.cz" />
    <target host="statistiky.cesky-hosting.cz" />
    <target host="chat.cesky-hosting.cz" />

    <rule from="^http:"
            to="https:" />
</ruleset>
