<!-- 

 	Invalid certificate:

		- goteborgsgirot.expressen.se (mismatch)
-->

<ruleset name="Expressen.se">

	<target host="expressen.se" />
	<target host="www.expressen.se" />

	<target host="annons.expressen.se" />
	<target host="bloggar.expressen.se" />
	<target host="etidning.expressen.se" />
	<target host="extra.expressen.se" />
	<target host="kampanj.expressen.se" />
	<target host="login.expressen.se" />
	<target host="magasin.expressen.se" />
	<target host="mittkok.expressen.se" />
	<target host="rabattkoder.expressen.se" />
	<target host="spel.expressen.se" />

	<rule from="^http:" to="https:" />
	
</ruleset>
