
<!--
Disabled by https-everywhere-checker because:
Fetch error: http://kontakt.get.no/ => https://kontakt.get.no/: (6, 'Could not resolve host: kontakt.get.no')
Fetch error: http://zendesk.get.no/ => https://zendesk.get.no/: Too many redirects while fetching 'https://zendesk.get.no/'

	Nonfunctional hosts in *get.no:

		- mobil ᵈ
		- speedtest ʳ

	ᵈ Dropped
	ʳ Refused


	Problematic hosts in *get.no:

		- kundehenvendelse ᵐ
		- villa ᵐ ᵘ

	ᵐ Mismatched
	ᵘ Untrusted root


	Insecure cookies are set for these hosts:

		- bedrift.get.no
		- getsafe.get.no
		- login.get.no
		- www.get.no


	Mixed content:

		- Images on bedrift from $self ˢ

	ˢ Secured by us, see https://www.paulirish.com/2010/the-protocol-relative-url/

-->
<ruleset name="Get.no (partial)" default_off='failed ruleset test'>

	<target host="get.no" />
	<target host="app.get.no" />
	<target host="bedrift.get.no" />
	<target host="devices.get.no" />
	<target host="getsafe.get.no" />
	<target host="kontakt.get.no" />
	<target host="login.get.no" />
	<target host="sky.get.no" />
	<target host="www.get.no" />
	<target host="zendesk.get.no" />


	<!--	Not secured by server:
					-->
	<!--securecookie host="^bedrift\.get\.no$" name="^PHPSESSID$" /-->
	<!--securecookie host="^getsafe\.get\.no$" name="^(?:JSESSIONID|JTBSC01|accept_language)$" /-->
	<!--securecookie host="^(?:login|www)\.get\.no$" name="^BIGipServer" /-->

	<securecookie host="^\." name="^_ga(?:t?$|t_)" />
	<securecookie host="^\w" name=".+" />


	<rule from="^http:"
		to="https:" />

</ruleset>
