<!--
	For other HK government coverage, see GovHK.xml.

	Invalid certificate:
		hkpl.gov.hk
		hkclweb.hkpl.gov.hk
		portal-216.hkpl.gov.hk
		support.hkpl.gov.hk

	No working URL known:
		epay.hkpl.gov.hk

	Redirect to HTTP:
		ask.hkpl.gov.hk

-->
<ruleset name="Hong Kong Public Libraries">
	<target host="hkpl.gov.hk" />
	<target host="www.hkpl.gov.hk" />
	<target host="ebookauth.hkpl.gov.hk" />
	<target host="ezproxy.hkpl.gov.hk" />
	<target host="mmis.hkpl.gov.hk" />
	<target host="mobileapp.hkpl.gov.hk" />
	<target host="webcat.hkpl.gov.hk" />

	<rule from="^http://hkpl\.gov\.hk/"
		to="https://www.hkpl.gov.hk/" />

	<rule from="^http:" to="https:" />
</ruleset>
