<!--
	Cert mismatch:
		- epaper.merkur.de
		- epaperapp.merkur.de
		- epaperkiosk.merkur.de
		- webviewer.merkur.de
-->

<ruleset name="Merkur.de">

	<target host="merkur.de" />
	<target host="www.merkur.de" />
	<target host="autoanzeigen.merkur.de" />
	<target host="druckhaustour.merkur.de" />
	<target host="immobilien.merkur.de" />
	<target host="jobs.merkur.de" />
	<target host="markt.merkur.de" />
	<target host="media.merkur.de" />
	<target host="playground.merkur.de" />
	<target host="promo.merkur.de" />
	<target host="trauer.merkur.de" />
	<target host="www.trauer.merkur.de" />
	<target host="veranstaltungen.merkur.de" />

	<test url="http://promo.merkur.de/abo/epaper/" />

	<rule from="^http://www\.trauer\.merkur\.de/" to="https://trauer.merkur.de/"/>

	<securecookie host=".+" name=".+" />

	<rule from="^http:" to="https:"/>

</ruleset>
