<!--
drweb.metro-set.ru ²
dtx.metro-set.ru ⁴
login.metro-set.ru ²
mx.metro-set.ru ³
ns1.metro-set.ru ²
ns2.metro-set.ru ²
ns3.metro-set.ru ²
nu.metro-set.ru ³
gw.nu.metro-set.ru ³
clips-001-cab2.nv.metro-set.ru ³
clips-002-cab2.nv.metro-set.ru ³
g1-s1-cab1.nv.metro-set.ru ²
g3-28-cab1.nv.metro-set.ru ²
lo-sw1-cab1.nv.metro-set.ru ³
vlan13-rb-cab2.nv.metro-set.ru ³
vlan13-sw1-cab1.nv.metro-set.ru ²
vlan14-rb-cab2.nv.metro-set.ru ³
vlan14-sw1-cab1.nv.metro-set.ru ³
pns.metro-set.ru ³
sg.metro-set.ru ³
clips-fail.sg.metro-set.ru ³
git.sg.metro-set.ru ³
gw-guestnet.sg.metro-set.ru ³
gw-nat.sg.metro-set.ru ³
gw-se.sg.metro-set.ru ³
gw-surgut.sg.metro-set.ru ²
login1.sg.metro-set.ru ³
login2.sg.metro-set.ru ³
mx.sg.metro-set.ru ³
ns1.sg.metro-set.ru ³
ns2.sg.metro-set.ru ³
speedtest.sg.metro-set.ru ³
userdns.sg.metro-set.ru ³
tech.metro-set.ru ³
tm.metro-set.ru ³
gw.tm.metro-set.ru ³
gw-ektix.tm.metro-set.ru ²
gw-mskix.tm.metro-set.ru ³
mx.tm.metro-set.ru ²
ts.metro-set.ru ²
cabinet.metro-set.ru different content
cabinet-old.metro-set.ru different content
redirect.metro-set.ru different content


² refused
³ timed out
⁴ self signed
-->
<ruleset name="metro-set.ru">
	<target host="metro-set.ru" />
	<target host="www.metro-set.ru" />
	<target host="cabinet-news.metro-set.ru" />
	<target host="dp.metro-set.ru" />
	<target host="eurosport.metro-set.ru" />
	<target host="old.metro-set.ru" />
	<target host="pay.metro-set.ru" />
	<target host="surgut.metro-set.ru" />

	<rule from="^http:" to="https:" />
</ruleset>
