<!--
	Problematic domains:

	Invalid certs:
		- books.mingpao.com (incomplete certificate chain)
		- www.jump.mingpao.com
		- www.life.mingpao.com

	SSL error: 
		- mobilenews.mingpao.com		
		- premium.mingpao.com
		- tssl.mingpao.com
		- video.mingpao.com

	Mixed content:
		- car.mingpao.com
		- jump.mingpao.com
		- jumpuat.mingpao.com
		- video3.mingpao.com
		- video4.mingpao.com

	Different content in HTTPS:
		- ce2017.mingpao.com
		- eduexpo.mingpao.com
		- fyp2016.mingpao.com
		- happypama2.mingpao.com
		- health2.mingpao.com
		- oly2016.mingpao.com
		- ppleak2016.mingpao.com
		- wimbledon.mingpao.com
		- wimbledon2016.mingpao.com

	Timeout:
		- code.mingpao.com
		- ebook.mingpao.com
		- indepth.mingpao.com
		- link.mingpao.com
		- reading.mingpao.com
		- studentreporter.mingpao.com

	Refused:
		- mpdeluxe.mingpao.com

	No working URL known:
		- fs1.mingpao.com
		- fs2.mingpao.com
		- ol2.mingpao.com

-->
<ruleset name="MingPao.com">
	<target host="mingpao.com" />
	<target host="www.mingpao.com" />
	<target host="creative.mingpao.com" />
	<target host="education.mingpao.com" />
	<target host="eletter.mingpao.com" />
	<target host="english.mingpao.com" />
	<target host="fs.mingpao.com" />
		<test url="http://fs.mingpao.com/ins/20141008/s00001/1412782353076_A79F8ECD26DFA2241F3FC085E3A03B9F.pdf" />
	<target host="happypama.mingpao.com" />
	<target host="health.mingpao.com" />
	<target host="jump.mingpao.com" />
	<target host="jump2.mingpao.com" />
	<target host="jumpuat.mingpao.com" />
	<target host="jupas.mingpao.com" />
	<target host="life.mingpao.com" />
	<target host="life2.mingpao.com" />
	<target host="m.mingpao.com" />
	<target host="marketing.mingpao.com" />
	<target host="marketing2.mingpao.com" />
		<test url="http://marketing2.mingpao.com/htm/china_enterprise_2011/htm/album.htm" />
	<target host="member.mingpao.com" />
	<target host="news.mingpao.com" />
	<target host="news1.mingpao.com" />
	<target host="news2.mingpao.com" />
	<target host="ol.mingpao.com" />
	<target host="www.ol.mingpao.com" />
	<target host="search.mingpao.com" />
	<target host="startup.mingpao.com" />

	<rule from="^http://www\.ol\.mingpao\.com/" to="https://ol.mingpao.com/" />
	<rule from="^http:" to="https:" />
</ruleset>
