<!--
	For related hidden service rules, see osf22p3lmweopgho.onion.xml

apps.opensocietyfoundations.org ³
eucoloexch1.opensocietyfoundations.org ³
eucoloexch2.opensocietyfoundations.org ³
eulondexch1.opensocietyfoundations.org ³
eulondexch2.opensocietyfoundations.org ³
eulondras.opensocietyfoundations.org ³
eupestexch1.opensocietyfoundations.org ³
eupestexch2.opensocietyfoundations.org ³
eupestras.opensocietyfoundations.org ³
auth.gslb.opensocietyfoundations.org ¹
mail.gslb.opensocietyfoundations.org ¹
sendgrid.opensocietyfoundations.org ¹
o1.sendgrid.opensocietyfoundations.org ³
usargoexch1.opensocietyfoundations.org ³
usargoexch2.opensocietyfoundations.org ³
usargoras.opensocietyfoundations.org ³
uscoloexch1.opensocietyfoundations.org ³
uscoloexch2.opensocietyfoundations.org ³
ttf.visualizingdata.opensocietyfoundations.org ¹
webmail.opensocietyfoundations.org ³


¹ mismatch
³ timed out
-->
<ruleset name="opensocietyfoundations.org">
	<target host="opensocietyfoundations.org" />
	<target host="www.opensocietyfoundations.org" />
	<target host="auth.opensocietyfoundations.org" />
	<target host="autheu.opensocietyfoundations.org" />
	<target host="authus.opensocietyfoundations.org" />
	<target host="autodiscover.opensocietyfoundations.org" />
	<target host="eumail.opensocietyfoundations.org" />
	<target host="mail.opensocietyfoundations.org" />
	<target host="static.opensocietyfoundations.org" />
	<target host="usmail.opensocietyfoundations.org" />

	<rule from="^http:" to="https:" />
</ruleset>
