<!--
	Related OpenStretMap rulesets:
		- OpenStreetMap.de.xml
		- OSM_Foundation.xml

	Invalid certificate:
		- analyser
		- cluster-ovh
		- comcommaker
		- garmin
		- osm103
		- osm23
		- owncloud
		- planet
		- polygons
		- proxy108
		- proxy117
		- rawedit
		- status
		- tiles
		- wms

	HTTP != HTTPS:
		- live
		- buildbot.osmose

	Connection refused:
		- nantes
		- nomino
		- normandie
		- osm102
		- osm134
		- dev.www

	Timeout:
		- export
		- osm16
		- opendata.osmose
		- suivi
		- backup.umap
-->
<ruleset name="Openstreetmap.fr">

    <target host="openstreetmap.fr" />
    <target host="www.openstreetmap.fr" />
    <target host="adherents.openstreetmap.fr" />
    <target host="ae.openstreetmap.fr" />
    <target host="dev.analyser.openstreetmap.fr" />
    <target host="api.openstreetmap.fr" />
    <target host="api-pic4carto.openstreetmap.fr" />
    <target host="bano.openstreetmap.fr" />
    <target host="dev.bano.openstreetmap.fr" />
    <target host="bato.openstreetmap.fr" />
    <target host="cachelyon.openstreetmap.fr" />
    <target host="cadastre.openstreetmap.fr" />
    <target host="tms.cadastre.openstreetmap.fr" />
    <target host="dev.comcommaker.openstreetmap.fr" />
    <target host="docs.openstreetmap.fr" />
    <target host="download.openstreetmap.fr" />
    <target host="forum.openstreetmap.fr" />
    <target host="dev.forum.openstreetmap.fr" />
    <target host="imagery.openstreetmap.fr" />
    <target host="josm-dev.openstreetmap.fr" />
    <target host="layers.openstreetmap.fr" />
    <target host="a.layers.openstreetmap.fr" />
    <target host="b.layers.openstreetmap.fr" />
    <target host="c.layers.openstreetmap.fr" />
    <target host="listes.openstreetmap.fr" />
    <target host="dev.listes.openstreetmap.fr" />
    <target host="maposmatic.openstreetmap.fr" />
    <target host="monitor.openstreetmap.fr" />
    <target host="munin.openstreetmap.fr" />
    <target host="next.openstreetmap.fr" />
    <target host="nextcloud.openstreetmap.fr" />
    <target host="osm101.openstreetmap.fr" />
    <target host="osm104.openstreetmap.fr" />
    <target host="osm105.openstreetmap.fr" />
    <target host="osm110.openstreetmap.fr" />
    <target host="osm13.openstreetmap.fr" />
    <target host="osm138.openstreetmap.fr" />
    <target host="osm2pgsql-monde.openstreetmap.fr" />
    <target host="osmma.openstreetmap.fr" />
    <target host="osmose.openstreetmap.fr" />
    <target host="beta.osmose.openstreetmap.fr" />
    <target host="dev.osmose.openstreetmap.fr" />
    <target host="overpass.openstreetmap.fr" />
    <target host="peertube.openstreetmap.fr" />
    <target host="petitereine.openstreetmap.fr" />
    <target host="prev.openstreetmap.fr" />
    <target host="proxy-ign.openstreetmap.fr" />
    <target host="sotm2018.openstreetmap.fr" />
    <target host="sotm2019.openstreetmap.fr" />
    <target host="taginfo.openstreetmap.fr" />
    <target host="dev.taginfo.openstreetmap.fr" />
    <target host="tile.openstreetmap.fr" />
    <target host="a.tile.openstreetmap.fr" />
    <target host="b.tile.openstreetmap.fr" />
    <target host="c.tile.openstreetmap.fr" />
    <target host="tile-a.openstreetmap.fr" />
    <target host="tile-b.openstreetmap.fr" />
    <target host="tile-c.openstreetmap.fr" />
    <target host="tilecache.openstreetmap.fr" />
    <target host="trac.openstreetmap.fr" />
    <target host="umap.openstreetmap.fr" />
    <target host="dev.umap.openstreetmap.fr" />

    <securecookie host=".+" name=".+" />

    <rule from="^http:" to="https:" />

</ruleset>
