<ruleset name="Phillips Academy">

	<target host="andover.edu" />
	<target host="www.andover.edu" />
	<target host="panet.andover.edu" />
	<target host="canvas.andover.edu" />
	<target host="colwizlive.andover.edu" />
	<target host="sso.andover.edu" />
	<target host="studentreports.andover.edu" />
	<target host="mypassword.andover.edu" />
	<target host="student.andover.edu" />
	<target host="patechmasters.com" />
	<target host="*.patechmasters.com" />

	<!-- These are internal hosts or require special ports, but can still use protection: -->
	<target host="printon.andover.edu" />
	<target host="mail.andover.edu" />
	<target host="sslvpn.andover.edu" />
	
	<securecookie host=".+" name=".+" />
	
	<rule from="^http://andover\.edu/"
		to="https://www.andover.edu/" />
	<rule from="^http:"
		to="https:" />

</ruleset>
