<!--
	For other US government coverage, see US-government.xml.

-->
<ruleset name="US Social Security Administration">

	<target host="socialsecurity.gov" />
	<target host="*.socialsecurity.gov" />
	<target host="ssa.gov" />
	<target host="*.ssa.gov" />


	<securecookie host="^((www)?\.)?socialsecurity\.gov$" name=".+" />
	<securecookie host="^((ftp|secure|stats|www)?\.)?ssa\.gov$" name=".+" />


	<rule from="^http(://(?:www\.)?|s://)socialsecurity\.gov/"
		to="https://www.socialsecurity.gov/" />

	<rule from="^http(://(?:(?:ftp|www)\.)?|s://(?:www\.)?)ssa\.gov/"
		to="https://www.socialsecurity.gov/" />

	<rule from="^http://s(ecure|tats)\.ssa\.gov/"
		to="https://s$1.ssa.gov/" />

</ruleset>
