<!--
	Insecure cookies are set for these hosts:

		- download.teamviewer.com
		- go.teamviewer.com
		- meeting.teamviewer.com
		- www.teamviewer.com

-->
<ruleset name="Teamviewer.com">

	<!--	Direct rewrites:
				-->
	<target host="teamviewer.com" />
	<target host="download.teamviewer.com" />
	<target host="downloadeu1.teamviewer.com" />
	<target host="downloadeu3.teamviewer.com" />
	<target host="go.teamviewer.com" />
	<target host="login.teamviewer.com" />
	<target host="meeting.teamviewer.com" />
	<target host="wa103.teamviewer.com" />
	<target host="wa236.teamviewer.com" />
	<target host="www.teamviewer.com" />


	<!--	Not secured by server:
					-->
	<!--securecookie host="^www\.teamviewer\.com$" name="^(?:ASP\.NET_SessionId|shortCountry)$" /-->

	<securecookie host="^(?:.*\.)?teamviewer.com$" name=".+" />


	<rule from="^http:"
		to="https:" />

</ruleset>
