<!--
	For other Tilda coverage, see Tilda.cc.xml.

	Problematic subdomains:
		- api (mismatched, CN: *.tilda.ws)
-->

<ruleset name="TildaCDN.com">
	<target host="assets.tildacdn.com" />
	<target host="forms.tildacdn.com" />
	<target host="geo.tildacdn.com" />
	<target host="mail.tildacdn.com" />
	<target host="stat.tildacdn.com" />
	<target host="static.tildacdn.com" />
	<target host="upload.tildacdn.com" />

	<securecookie host=".+" name=".+" />

	<rule from="^http:" to="https:" />
</ruleset>
