<!--
	Non-functional hosts
		Couldn't connect to server:
		- chancellor.ucsd.edu
		- communication.ucsd.edu
		- founders.ucsd.edu
		- universitycenters.ucsd.edu

		SSL connect error:
		- athletics.ucsd.edu

		SSL peer certificate was not OK:
		- www.alumni.ucsd.edu
		- giftplanning.ucsd.edu
		- www.giftplanning.ucsd.edu
		- ogs-calendar.ucsd.edu
		- www.studentsupport.ucsd.edu
		- vac.ucsd.edu

		Peer certificate cannot be authenticated with given CA certificates:
		- campaign.ucsd.edu
		- giving.ucsd.edu
		- nanoengineering.ucsd.edu
		- pharmacy.ucsd.edu

		Incomplete certificate chain error:
		- alumni.ucsd.edu

		Different content:
		- diversity.ucsd.edu
		- provost.ucsd.edu

		Mixed content blocking (MCB) triggered:
		- career.ucsd.edu
		- m.ucsd.edu
-->
<ruleset name="University of California San Diego (partial)">
	<target host="ucsd.edu" />
	<target host="www.ucsd.edu" />

	<target host="act.ucsd.edu" />
	<target host="academicconnections.ucsd.edu" />
	<target host="acms.ucsd.edu" />
	<target host="admissions.ucsd.edu" />
	<target host="apol-recruit.ucsd.edu" />
	<target host="aquarium.ucsd.edu" />
	<target host="assets.ucsd.edu" />

	<target host="calendar.ucsd.edu" />
	<target host="chemistry.ucsd.edu" />
	<target host="cinfo.ucsd.edu" />
	<target host="commons.ucsd.edu" />
	<target host="courses.ucsd.edu" />
	<target host="cse.ucsd.edu" />

	<target host="disabilities.ucsd.edu" />
	<target host="doctors.ucsd.edu" />

	<target host="eaop.ucsd.edu" />
	<target host="economics.ucsd.edu" />
	<target host="extension.ucsd.edu" />

	<target host="facilities.ucsd.edu" />
	<target host="facultydiversity.ucsd.edu" />
	<target host="foundation.ucsd.edu" />

	<target host="git.ucsd.edu" />
	<target host="globalhealthprogram.ucsd.edu" />
	<target host="grad.ucsd.edu" />
	<target host="apply.grad.ucsd.edu" />

	<target host="hdh.ucsd.edu" />
	<target host="health.ucsd.edu" />
	<target host="healthbeat.ucsd.edu" />
	<target host="history.ucsd.edu" />

	<target host="library.ucsd.edu" />
	<target host="libraries.ucsd.edu" />
	<target host="libguides.ucsd.edu" />

	<target host="maps.ucsd.edu" />
	<target host="marketplace.ucsd.edu" />
	<target host="math.ucsd.edu" />
	<target host="mentorship.ucsd.edu" />
	<target host="meded.ucsd.edu" />
	<target host="mobile.ucsd.edu" />

	<target host="parents.ucsd.edu" />
	<target host="plandesignbuild.ucsd.edu" />
	<target host="profiles.ucsd.edu" />
	<target host="providers.ucsd.edu" />
	<target host="psychology.ucsd.edu" />

	<target host="recreation.ucsd.edu" />
	<target host="resnet.ucsd.edu" />
	<target host="roosevelt.ucsd.edu" />

	<target host="scripps.ucsd.edu" />
	<target host="software.ucsd.edu" />
	<target host="structures.ucsd.edu" />
	<target host="www.structures.ucsd.edu" />
	<target host="students.ucsd.edu" />
	<target host="studentsupport.ucsd.edu" />
	<target host="sustainability.ucsd.edu" />

	<target host="ted.ucsd.edu" />
	<target host="transportation.ucsd.edu" />
	<target host="tritoned.ucsd.edu" />

	<target host="ucsdnews.ucsd.edu" />
	<target host="ugcbo.ucsd.edu" />

	<target host="wellness.ucsd.edu" />
	<target host="women.ucsd.edu" />

	<rule from="^http:" to="https:" />
</ruleset>
