<ruleset name="University of Applied Sciences Kiel">

	<target host="fh-kiel.de" />
	<target host="www.fh-kiel.de" />
	<target host="email.fh-kiel.de" />
	<target host="student.fh-kiel.de" />
	<target host="www.email.fh-kiel.de" />
	<target host="www.student.fh-kiel.de" />
	<target host="ida.fh-kiel.de" />
	<target host="hrzsophos.hrz.isc.fh-kiel.de" />
	<target host="modulanmeldung.fh-kiel.de" />
	<target host="module.fh-kiel.de" />
	<target host="vpn.fh-kiel.de" />


	<securecookie host="^(?:(?:(?:www)?|(?:www\.)?(?:email|student)|hrzsophos\.hrz\.isc|ida|modulanmeldung|module|vpn)\.)?fh-kiel.de$" name=".+" />


	<rule from="^http://(?:www\.)?fh-kiel\.de/"
		to="https://www.fh-kiel.de/" />

	<rule from="^http://(?:www\.)?(email|student)\.fh-kiel\.de/"
		to="https://$1.fh-kiel.de/" />


	<rule from="^http:" to="https:" />
</ruleset>
