
<!--
Disabled by https-everywhere-checker because:
Fetch error: http://sitemason.vanderbilt.edu/ => https://sitemason.vanderbilt.edu/: (7, 'Failed to connect to sitemason.vanderbilt.edu port 443: No route to host')
 see Vanderbilt.org-falsemixed.xml for other rules -->
<ruleset name="Vanderbilt.edu (partial)" default_off='failed ruleset test'>
	<target host=            "hr.vanderbilt.edu" />
	<target host=        "www.mc.vanderbilt.edu" />
	<target host=            "mc.vanderbilt.edu" />
	<target host=            "my.vanderbilt.edu" />
	<target host="phonedirectory.vanderbilt.edu" />
	<target host=     "sitemason.vanderbilt.edu" />
        <securecookie host="^events\.vanderbilt\.edu$" name=".+" />
        <securecookie host="^www\.mc\.vanderbilt\.edu$" name=".+" />
	<securecookie host="^mc\.vanderbilt\.edu$" name=".+" />
        <securecookie host="^my\.vanderbilt\.edu$" name=".+" />
        <securecookie host="^phonedirectory\.vanderbilt\.edu$" name=".+" />
	<rule from="^http:"
		to="https:" />
</ruleset>
