<!--
	Nonfunctional hosts in *.vse.sk:

	connection refused:
		- b2w.vse.sk
	timeout on https:
		- login.vse.sk
		- gw.vse.sk
		- mailgw.vse.sk
		- www.mailgw.vse.sk
		- pomoc.vse.sk
		- sts.vse.sk
		- www.sts.vse.sk
		- wlc.vse.sk
-->
<ruleset name="Vse.sk">
	<target host="vse.sk" />
	<target host="www.vse.sk" />
	<target host="b2b.vse.sk" />
	<target host="csg.vse.sk" />
	<target host="mail.vse.sk" />
	<target host="nsg.vse.sk" />
	<target host="pdasync.vse.sk" />
	<target host="vpn.vse.sk" />

	<rule from="^http:" to="https:" />
</ruleset>
